pidgeotto-1.0.0.dist-info/licenses/LICENSE
pidgey/__init__.py
pidgey/builder.py
pidgey/creator.py
pidgey/pidgey.py
pidgey/server.py
pidgeotto-1.0.0.dist-info/METADATA
pidgeotto-1.0.0.dist-info/WHEEL
pidgeotto-1.0.0.dist-info/entry_points.txt
pidgeotto-1.0.0.dist-info/top_level.txt
pidgeotto-1.0.0.dist-info/RECORD
