Metadata-Version: 2.4
Name: pidgeotto
Version: 1.0.0
Summary: A minimal, fast static site generator built for Markdown lovers.
Home-page: https://gitlab.com/niharokz/pidgeotto
Author: Nihar
Author-email: hi@nihars.com
License: MIT
Keywords: python,static site generator,markdown,Jinja2,pyyaml
Classifier: Development Status :: 5 - Production/Stable
Classifier: Intended Audience :: Developers
Classifier: License :: OSI Approved :: MIT License
Classifier: Programming Language :: Python :: 3
Classifier: Programming Language :: Python :: 3.6
Classifier: Programming Language :: Python :: 3.7
Classifier: Programming Language :: Python :: 3.8
Classifier: Programming Language :: Python :: 3.13
Classifier: Operating System :: OS Independent
License-File: LICENSE
Requires-Dist: markdown2
Requires-Dist: Jinja2
Requires-Dist: pyyaml
Requires-Dist: rich
Dynamic: author
Dynamic: author-email
Dynamic: classifier
Dynamic: description
Dynamic: description-content-type
Dynamic: home-page
Dynamic: keywords
Dynamic: license
Dynamic: license-file
Dynamic: requires-dist
Dynamic: summary
